sarvesh/__init__.py
sarvesh-0.1.0.dist-info/METADATA
sarvesh-0.1.0.dist-info/WHEEL
sarvesh-0.1.0.dist-info/RECORD
