Metadata-Version: 2.1
Name: sarvesh
Version: 0.1.0
Summary: 
Author: Sarveshwaran J
Author-email: sarveshwaran.j@ewallsolutions.com
Requires-Python: >=3.10,<4.0
Classifier: Programming Language :: Python :: 3
Classifier: Programming Language :: Python :: 3.10
Classifier: Programming Language :: Python :: 3.11
Classifier: Programming Language :: Python :: 3.12
Requires-Dist: flask (>=2.0.1,<3.0.0)
Requires-Dist: numpy (>=1.21.0,<2.0.0)
Requires-Dist: pandas (>=1.3.0,<2.0.0)
Requires-Dist: requests (>=2.25.1,<3.0.0)
